vbelts/__init__.py
vbelts/belt.py
vbelts/length.py
vbelts/power.py
vbelts/pulley.py
vbelts/speed.py
vbelts/util.py
vbelts/data/HiPower_a_pa.csv
vbelts/data/HiPower_a_pb.csv
vbelts/data/HiPower_b_pa.csv
vbelts/data/HiPower_b_pb.csv
vbelts/data/HiPower_c_pa.csv
vbelts/data/HiPower_c_pb.csv
vbelts/data/HiPower_d_pa.csv
vbelts/data/HiPower_d_pb.csv
vbelts/data/HiPower_fcc.csv
vbelts/data/HiPower_length.csv
vbelts/data/SuperHC_3v_pa.csv
vbelts/data/SuperHC_3v_pb.csv
vbelts/data/SuperHC_5v_pa.csv
vbelts/data/SuperHC_5v_pb.csv
vbelts/data/SuperHC_8v_pa.csv
vbelts/data/SuperHC_8v_pb.csv
vbelts/data/SuperHC_fcc.csv
vbelts/data/SuperHC_length.csv
vbelts/data/fcac_contact_arc.csv
vbelts/data/fric_coef.csv
vbelts/data/hi_power_diam.csv
vbelts/data/super_hc_diam.csv
vbelts-0.3.10.dist-info/LICENSE.txt
vbelts-0.3.10.dist-info/METADATA
vbelts-0.3.10.dist-info/WHEEL
vbelts-0.3.10.dist-info/top_level.txt
vbelts-0.3.10.dist-info/RECORD
