Metadata-Version: 2.1
Name: vbelts
Version: 0.3.10
Summary: Utilities for v-belt dimensioning
Home-page: https://github.com/traumatic-monotype/vbelts
Author: Glademir Karpinski Junior, Hector Balke Nodari
Author-email: gkarpinskijr@gmail.com, hectornodari@gmail.com
License: UNKNOWN
Platform: UNKNOWN
Classifier: Development Status :: 4 - Beta
Classifier: Environment :: Console
Classifier: Natural Language :: English
Classifier: Programming Language :: Python :: 3 :: Only
Classifier: Programming Language :: Python :: 3.7
Classifier: Programming Language :: Python :: 3.8
Classifier: Topic :: Scientific/Engineering
Classifier: License :: OSI Approved :: BSD License
Classifier: Operating System :: OS Independent
Provides-Extra: dev
Requires-Dist: pytest (==6.0.1) ; extra == 'dev'
Requires-Dist: check-manifest (==0.42) ; extra == 'dev'
Requires-Dist: sphinx (==3.2.1) ; extra == 'dev'
Requires-Dist: autodoc (==0.5.0) ; extra == 'dev'
Requires-Dist: sphinx-rtd-theme (==0.5.0) ; extra == 'dev'
